makefunc/__init__.py
makefunc/core/__init__.py
makefunc/tests/__init__.py
makefunc/tests/test_1984.py
makefunc-0.0.3.dist-info/LICENSE.txt
makefunc-0.0.3.dist-info/METADATA
makefunc-0.0.3.dist-info/WHEEL
makefunc-0.0.3.dist-info/top_level.txt
makefunc-0.0.3.dist-info/RECORD
