Metadata-Version: 2.1
Name: makefunc
Version: 0.0.3
Summary: makefunc
Author-email: Johannes <johannes-programming@mailfence.com>
License: The MIT License (MIT)
Project-URL: Documentation, https://pypi.org/project/makefunc
Project-URL: Download, https://pypi.org/project/makefunc/#files
Project-URL: Index, https://pypi.org/project/makefunc/
Project-URL: Source, https://github.com/johannes-programming/makefunc
Project-URL: Website, https://makefunc.johannes-programming.online/
Classifier: Development Status :: 2 - Pre-Alpha
Classifier: License :: OSI Approved :: MIT License
Classifier: Programming Language :: Python
Classifier: Programming Language :: Python :: 3
Classifier: Programming Language :: Python :: 3 :: Only
Requires-Python: >=3.8
License-File: LICENSE.txt
